{"cameraMode":{"drawMode":0,"name":"Shaded","section":"Shading Mode"},"sceneLighting":true,"audioPlay":false,"sceneViewState":{"showFog":true,"showMaterialUpdate":false,"showSkybox":true,"showFlares":true,"showImageEffects":true,"showParticleSystems":true,"showVisualEffectGraphs":true,"m_FxEnabled":true},"in2DMode":false,"pivot":{"x":-2.0405101776123049,"y":0.7496881484985352,"z":1.5071992874145508},"rotation":{"x":-0.0882897675037384,"y":0.8989551663398743,"z":-0.21315036714076997,"w":-0.37235939502716067},"size":10.0,"orthographic":false}